ii_drf_pagination/__init__.py
ii_drf_pagination/pagination.py
ii_drf_pagination/settings.py
ii_drf_pagination-0.1.dist-info/DESCRIPTION.rst
ii_drf_pagination-0.1.dist-info/LICENSE.txt
ii_drf_pagination-0.1.dist-info/METADATA
ii_drf_pagination-0.1.dist-info/RECORD
ii_drf_pagination-0.1.dist-info/WHEEL
ii_drf_pagination-0.1.dist-info/metadata.json
ii_drf_pagination-0.1.dist-info/top_level.txt
