Metadata-Version: 2.0
Name: ii-drf-pagination
Version: 0.1
Summary: ideallical django-restframework pagination
Home-page: https://github.com/ideallical/ii-drf-pagination
Author: ideallical
Author-email: info@ideallical.com
License: BSD
Download-URL: https://github.com/ideallical/ii-drf-pagination/archive/0.1.tar.gz
Keywords: testing,drf,pagination
Platform: UNKNOWN
